rocker/__init__.py
rocker/cli.py
rocker/core.py
rocker/em.py
rocker/extensions.py
rocker/git_extension.py
rocker/nvidia_extension.py
rocker/os_detector.py
rocker/rmw_extension.py
rocker/ssh_extension.py
rocker/ulimit_extension.py
rocker/volume_extension.py
rocker/templates/Dockerfile.em
rocker/templates/bash_cmd_snippet.Dockerfile.em
rocker/templates/cuda_snippet.Dockerfile.em
rocker/templates/dev_helpers_snippet.Dockerfile.em
rocker/templates/nvidia_preamble.Dockerfile.em
rocker/templates/nvidia_snippet.Dockerfile.em
rocker/templates/pulse_snippet.Dockerfile.em
rocker/templates/rmw_snippet.Dockerfile.em
rocker/templates/user_snippet.Dockerfile.em
rocker-0.2.19.dist-info/LICENSE
rocker-0.2.19.dist-info/METADATA
rocker-0.2.19.dist-info/WHEEL
rocker-0.2.19.dist-info/entry_points.txt
rocker-0.2.19.dist-info/top_level.txt
rocker-0.2.19.dist-info/RECORD
